README.md
setup.py
mol_tdn/__init__.py
mol_tdn/eos.py
mol_tdn/get_data.py
mol_tdn/molecule.py
mol_tdn/plot.py
mol_tdn.egg-info/PKG-INFO
mol_tdn.egg-info/SOURCES.txt
mol_tdn.egg-info/dependency_links.txt
mol_tdn.egg-info/requires.txt
mol_tdn.egg-info/top_level.txt
tests/__init__.py
tests/test_eos.py