Metadata-Version: 2.1
Name: mol-tdn
Version: 0.0.1
Summary: Tools for computing thermodynamic properties of molecular fluids
Home-page: https://github.com/danieleongari/mol-tdn
Author: Daniele Ongari
Author-email: daniele.ongari@gmail.com
License: Creative Commons
Platform: UNKNOWN
Classifier: Programming Language :: Python
Provides-Extra: testing
Provides-Extra: pre-commit
